prefect_azure/__init__.py
prefect_azure/_version.py
prefect_azure/blob_storage.py
prefect_azure/cosmos_db.py
prefect_azure/credentials.py
prefect_azure/ml_datastore.py
prefect_azure_dyvenia-0.1.0.dist-info/LICENSE
prefect_azure_dyvenia-0.1.0.dist-info/METADATA
prefect_azure_dyvenia-0.1.0.dist-info/WHEEL
prefect_azure_dyvenia-0.1.0.dist-info/entry_points.txt
prefect_azure_dyvenia-0.1.0.dist-info/top_level.txt
prefect_azure_dyvenia-0.1.0.dist-info/RECORD
