Metadata-Version: 2.1
Name: prefect-azure-dyvenia
Version: 0.1.0
Summary: Prefect tasks and subflows for interacting with Azure
Home-page: https://github.com/Trymzet/prefect-azure
Author: Prefect Technologies, Inc.
Author-email: help@prefect.io
License: Apache License 2.0
Keywords: prefect
Classifier: Natural Language :: English
Classifier: Intended Audience :: Developers
Classifier: Intended Audience :: System Administrators
Classifier: License :: OSI Approved :: Apache Software License
Classifier: Programming Language :: Python :: 3 :: Only
Classifier: Programming Language :: Python :: 3.7
Classifier: Programming Language :: Python :: 3.8
Classifier: Programming Language :: Python :: 3.9
Classifier: Programming Language :: Python :: 3.10
Classifier: Topic :: Software Development :: Libraries
Requires-Python: >=3.7
License-File: LICENSE
Requires-Dist: prefect
Provides-Extra: all_extras
Requires-Dist: azure-cosmos ; extra == 'all_extras'
Requires-Dist: azure-identity >=1.11.0 ; extra == 'all_extras'
Requires-Dist: azure-keyvault-secrets >=4.6.0 ; extra == 'all_extras'
Requires-Dist: azure-storage-blob ; extra == 'all_extras'
Requires-Dist: azureml-core ; extra == 'all_extras'
Provides-Extra: blob_storage
Requires-Dist: azure-storage-blob ; extra == 'blob_storage'
Provides-Extra: cosmos_db
Requires-Dist: azure-cosmos ; extra == 'cosmos_db'
Provides-Extra: key_vault
Requires-Dist: azure-keyvault-secrets >=4.6.0 ; extra == 'key_vault'
Requires-Dist: azure-identity >=1.11.0 ; extra == 'key_vault'
Provides-Extra: ml_datastore
Requires-Dist: azureml-core ; extra == 'ml_datastore'
